{
  "uuid": "dcaa49ce-e072-46e4-ac7e-2565e24776d0",
  "name": "Otenkotenki",
  "totalVotes": 96,
  "offlineEarned": 0,
  "votesToday": 0,
  "expeditions": [],
  "unclaimedRewards": {},
  "lastVotes": [
    {
      "year": 2022,
      "month": 3,
      "day": 30
    },
    {
      "year": 2022,
      "month": 4,
      "day": 1
    },
    {
      "year": 2022,
      "month": 4,
      "day": 3
    },
    {
      "year": 2022,
      "month": 4,
      "day": 4
    },
    {
      "year": 2022,
      "month": 4,
      "day": 5
    },
    {
      "year": 2022,
      "month": 4,
      "day": 6
    },
    {
      "year": 2022,
      "month": 4,
      "day": 7
    }
  ],
  "lastDailyClaim": {
    "year": 2022,
    "month": 4,
    "day": 7
  },
  "lastDayUpdated": {
    "year": 2022,
    "month": 4,
    "day": 7
  }
}